README
setup.py
cmndr/__init__.py
cmndr/commandbus.py
cmndr/middleware.py
cmndr.egg-info/PKG-INFO
cmndr.egg-info/SOURCES.txt
cmndr.egg-info/dependency_links.txt
cmndr.egg-info/top_level.txt
cmndr/exception/__init__.py
cmndr/exception/invalidmiddlewareexception.py
cmndr/handlers/__init__.py
cmndr/handlers/commandhandler.py
cmndr/handlers/middlewarehandler.py
cmndr/handlers/inflectors/__init__.py
cmndr/handlers/inflectors/callableinflector.py
cmndr/handlers/inflectors/inflector.py
cmndr/handlers/locators/__init__.py
cmndr/handlers/locators/inmemorylocator.py
cmndr/handlers/locators/lazyloadinginmemorylocator.py
cmndr/handlers/locators/locator.py
cmndr/handlers/nameextractors/__init__.py
cmndr/handlers/nameextractors/classnameextractor.py
cmndr/handlers/nameextractors/nameextractor.py