Metadata-Version: 1.0
Name: cmndr
Version: 1.0.4
Summary: A python commandbus implementation
Home-page: UNKNOWN
Author: Thomas Phil
Author-email: thomas@tphil.nl
License: UNKNOWN
Platform: UNKNOWN
